Operacoes.py
__init__.py
nicolascalclib-0.1.0.dist-info/licenses/LICENCE.md
nicolascalclib-0.1.0.dist-info/METADATA
nicolascalclib-0.1.0.dist-info/WHEEL
nicolascalclib-0.1.0.dist-info/top_level.txt
nicolascalclib-0.1.0.dist-info/RECORD
